hyperkitty-1.3.12.dist-info/METADATA
hyperkitty-1.3.12.dist-info/WHEEL
hyperkitty-1.3.12.dist-info/licenses/AUTHORS.txt
hyperkitty-1.3.12.dist-info/licenses/COPYING.txt
hyperkitty/__init__.py
hyperkitty/admin.py
hyperkitty/api/__init__.py
hyperkitty/api/attachment.py
hyperkitty/api/email.py
hyperkitty/api/mailinglist.py
hyperkitty/api/sender.py
hyperkitty/api/tag.py
hyperkitty/api/thread.py
hyperkitty/api/utils.py
hyperkitty/apps.py
hyperkitty/checks.py
hyperkitty/context_processors.py
hyperkitty/contrib/check_hk_import
hyperkitty/contrib/cleanarch3
hyperkitty/feed.py
hyperkitty/fixtures/first_start.json
hyperkitty/fixtures/tag_testdata.json
hyperkitty/forms.py
hyperkitty/jobs/__init__.py
hyperkitty/jobs/empty_threads.py
hyperkitty/jobs/new_lists_from_mailman.py
hyperkitty/jobs/orphan_emails.py
hyperkitty/jobs/recent_threads_cache.py
hyperkitty/jobs/sync_mailman.py
hyperkitty/jobs/thread_order_depth.py
hyperkitty/jobs/thread_starting_email.py
hyperkitty/jobs/update_and_clean_index.py
hyperkitty/jobs/update_index.py
hyperkitty/lib/__init__.py
hyperkitty/lib/analysis.py
hyperkitty/lib/compat.py
hyperkitty/lib/haystack.py
hyperkitty/lib/incoming.py
hyperkitty/lib/mailman.py
hyperkitty/lib/mockup.py
hyperkitty/lib/posting.py
hyperkitty/lib/renderer.py
hyperkitty/lib/user.py
hyperkitty/lib/utils.py
hyperkitty/lib/view_helpers.py
hyperkitty/locale/LINGUAS
hyperkitty/locale/af/LC_MESSAGES/django.po
hyperkitty/locale/am/LC_MESSAGES/django.po
hyperkitty/locale/an/LC_MESSAGES/django.po
hyperkitty/locale/ar/LC_MESSAGES/django.po
hyperkitty/locale/ast/LC_MESSAGES/django.po
hyperkitty/locale/az/LC_MESSAGES/django.po
hyperkitty/locale/be/LC_MESSAGES/django.po
hyperkitty/locale/bem/LC_MESSAGES/django.po
hyperkitty/locale/bg/LC_MESSAGES/django.po
hyperkitty/locale/bn/LC_MESSAGES/django.po
hyperkitty/locale/bo/LC_MESSAGES/django.po
hyperkitty/locale/br/LC_MESSAGES/django.po
hyperkitty/locale/bs/LC_MESSAGES/django.po
hyperkitty/locale/ca/LC_MESSAGES/django.po
hyperkitty/locale/ca@valencia/LC_MESSAGES/django.po
hyperkitty/locale/ce/LC_MESSAGES/django.po
hyperkitty/locale/ckb/LC_MESSAGES/django.po
hyperkitty/locale/co/LC_MESSAGES/django.po
hyperkitty-1.3.12.dist-info/RECORD
