Metadata-Version: 2.1
Name: HyperKitty
Version: 1.3.12
Summary: A web interface to access GNU Mailman v3 archives
Keywords: email
Author-Email: Mailman Developers <mailman-developers@python.org>
License: GPLv3
Classifier: Development Status :: 4 - Beta
Classifier: Framework :: Django
Classifier: License :: OSI Approved :: GNU General Public License v3 (GPLv3)
Classifier: Programming Language :: JavaScript
Classifier: Programming Language :: Python :: 3
Classifier: Topic :: Communications :: Email :: Mailing List Servers
Project-URL: Homepage, https://gitlab.com/mailman/hyperkitty
Requires-Python: >=3.9
Requires-Dist: django-compressor>=1.3
Requires-Dist: django-extensions>=1.3.7
Requires-Dist: django-gravatar2>=1.0.6
Requires-Dist: django-haystack>=2.8.0
Requires-Dist: django-q2>=1.0.0
Requires-Dist: django<5.1,>=4.2
Requires-Dist: django_mailman3>=1.3.13
Requires-Dist: djangorestframework>=3.0.0
Requires-Dist: flufl.lock>=4.0
Requires-Dist: mailmanclient>=3.3.3
Requires-Dist: mistune>=3.0
Requires-Dist: networkx>=2.0
Requires-Dist: python-dateutil>=2.0
Requires-Dist: robot-detection>=0.3
Requires-Dist: isort; extra == "dev"
Requires-Dist: Whoosh>=2.5.7; extra == "dev"
Requires-Dist: django-debug-toolbar; extra == "dev"
Requires-Dist: Whoosh>=2.5.7; extra == "test"
Requires-Dist: beautifulsoup4>=4.3.2; extra == "test"
Requires-Dist: lxml; extra == "test"
Requires-Dist: django-debug-toolbar; extra == "test"
Provides-Extra: dev
Provides-Extra: test
